decklizer/__init__.py
decklizer/app.py
decklizer/engine.py
decklizer/utils.py
decklizer/version.py
decklizer/data/200721_ New Way SCH W3-W6 W14 07.20.20.xlsx
decklizer/data/200725_WAVA Deckle Optimization Parameters Rev1.xlsx
"decklizer/data/New Way SCH W3-W6, W14 08.24.20.xlsx"
decklizer/tests/__init__.py
decklizer/tests/test.py
decklizer-0.1.3.dist-info/LICENSE
decklizer-0.1.3.dist-info/METADATA
decklizer-0.1.3.dist-info/WHEEL
decklizer-0.1.3.dist-info/top_level.txt
decklizer-0.1.3.dist-info/RECORD
