Metadata-Version: 2.1
Name: decklizer
Version: 0.1.3
Summary: Decklizer
Home-page: http://github.com/wesleybeckner/decklizer
Author: Wesley Beckner
Author-email: wesleybeckner@gmail.com
Maintainer: Wesley Beckner
Maintainer-email: wesleybeckner@gmail.com
License: MIT
Platform: OS Independent
Classifier: Development Status :: 3 - Alpha
Classifier: Environment :: Console
Classifier: Intended Audience :: Science/Research
Classifier: License :: OSI Approved :: MIT License
Classifier: Operating System :: OS Independent
Classifier: Programming Language :: Python
Classifier: Topic :: Scientific/Engineering
Requires: numpy
Requires: pandas
Requires: scipy
Requires-Dist: numpy
Requires-Dist: pandas
Requires-Dist: scipy
